setup.py
bixin_oauth2.egg-info/PKG-INFO
bixin_oauth2.egg-info/SOURCES.txt
bixin_oauth2.egg-info/dependency_links.txt
bixin_oauth2.egg-info/not-zip-safe
bixin_oauth2.egg-info/requires.txt
bixin_oauth2.egg-info/top_level.txt
pyoauth2/__init__.py
pyoauth2/client.py
pyoauth2/libs/__init__.py
pyoauth2/libs/access_token.py
pyoauth2/libs/auth_code.py
pyoauth2/libs/base.py
pyoauth2/libs/connection.py
pyoauth2/libs/errors.py
pyoauth2/libs/request.py
pyoauth2/libs/response.py
pyoauth2/libs/utils.py