Metadata-Version: 1.1
Name: bixin-oauth2
Version: 0.0.7
Summary: bixin oauth2 lib version
Home-page: https://github.com/haobtc/pyhaobtc/tree/master/haobtc_oauth2
Author: freeza91
Author-email: useyes91@gmail.com
License: MIT License
Keywords: Python,pyoauth2,bixin
Platform: any
Classifier: Environment :: Web Environment
Classifier: Intended Audience :: Developers
Classifier: License :: OSI Approved :: MIT License
Classifier: Operating System :: OS Independent
